<stg><name>copy_w5</name>


<trans_list>

<trans id="72" from="1" to="2">
<condition id="30">
<or_exp><and_exp></and_exp></or_exp>
</condition>
</trans>

<trans id="73" from="2" to="3">
<condition id="32">
<or_exp><and_exp><literal name="exitcond3" val="0"/>
</and_exp></or_exp>
</condition>
</trans>

<trans id="74" from="3" to="4">
<condition id="34">
<or_exp><and_exp><literal name="exitcond2" val="0"/>
</and_exp></or_exp>
</condition>
</trans>

<trans id="89" from="3" to="2">
<condition id="54">
<or_exp><and_exp><literal name="exitcond2" val="1"/>
</and_exp></or_exp>
</condition>
</trans>

<trans id="75" from="4" to="5">
<condition id="35">
<or_exp><and_exp><literal name="exitcond1" val="0"/>
</and_exp></or_exp>
</condition>
</trans>

<trans id="88" from="4" to="3">
<condition id="52">
<or_exp><and_exp><literal name="exitcond1" val="1"/>
</and_exp></or_exp>
</condition>
</trans>

<trans id="77" from="5" to="6">
<condition id="37">
<or_exp><and_exp></and_exp></or_exp>
</condition>
</trans>

<trans id="78" from="6" to="7">
<condition id="38">
<or_exp><and_exp></and_exp></or_exp>
</condition>
</trans>

<trans id="79" from="7" to="8">
<condition id="39">
<or_exp><and_exp></and_exp></or_exp>
</condition>
</trans>

<trans id="80" from="8" to="9">
<condition id="40">
<or_exp><and_exp></and_exp></or_exp>
</condition>
</trans>

<trans id="81" from="9" to="10">
<condition id="41">
<or_exp><and_exp></and_exp></or_exp>
</condition>
</trans>

<trans id="82" from="10" to="11">
<condition id="42">
<or_exp><and_exp></and_exp></or_exp>
</condition>
</trans>

<trans id="83" from="11" to="12">
<condition id="44">
<or_exp><and_exp></and_exp></or_exp>
</condition>
</trans>

<trans id="84" from="12" to="13">
<condition id="45">
<or_exp><and_exp><literal name="exitcond" val="0"/>
</and_exp></or_exp>
</condition>
</trans>

<trans id="87" from="12" to="4">
<condition id="50">
<or_exp><and_exp><literal name="exitcond" val="1"/>
</and_exp></or_exp>
</condition>
</trans>

<trans id="86" from="13" to="12">
<condition id="48">
<or_exp><and_exp></and_exp></or_exp>
</condition>
</trans>
</trans_list>



<state_list>

<state id="1" st_id="1">

<operation id="14" st_id="1" stage="1" lat="1">
<core>NULL</core>
<MemPortIdVec></MemPortIdVec>
<condition id="0">
<or_exp><and_exp></and_exp></or_exp>
</condition>

<Node id="4" bw="30" op_0_bw="30" op_1_bw="30">
<![CDATA[
:0  %c5_w_i11_read = call i30 @_ssdm_op_Read.ap_auto.i30(i30 %c5_w_i11)

]]></Node>
<StgValue><ssdm name="c5_w_i11_read"/></StgValue>
</operation>

<operation id="15" st_id="1" stage="1" lat="1">
<core>NULL</core>
<MemPortIdVec></MemPortIdVec>
<condition id="0">
<or_exp><and_exp></and_exp></or_exp>
</condition>

<Node id="5" bw="32" op_0_bw="30">
<![CDATA[
:1  %c5_w_i11_cast = zext i30 %c5_w_i11_read to i32

]]></Node>
<StgValue><ssdm name="c5_w_i11_cast"/></StgValue>
</operation>

<operation id="16" st_id="1" stage="1" lat="1">
<core>NULL</core>
<MemPortIdVec></MemPortIdVec>
<condition id="0">
<or_exp><and_exp></and_exp></or_exp>
</condition>

<Node id="6" bw="0" op_0_bw="0" op_1_bw="32" op_2_bw="0" op_3_bw="32" op_4_bw="32" op_5_bw="0" op_6_bw="32" op_7_bw="32" op_8_bw="0" op_9_bw="0" op_10_bw="0" op_11_bw="32" op_12_bw="32" op_13_bw="32" op_14_bw="32" op_15_bw="0" op_16_bw="0">
<![CDATA[
:2  call void (...)* @_ssdm_op_SpecInterface(float* %in_r, [6 x i8]* @p_str, i32 0, i32 0, [1 x i8]* @p_str1, i32 0, i32 48000, [12 x i8]* @p_str8, [6 x i8]* @p_str3, [1 x i8]* @p_str1, i32 16, i32 16, i32 16, i32 16, [1 x i8]* @p_str1, [1 x i8]* @p_str1)

]]></Node>
<StgValue><ssdm name=""/></StgValue>
</operation>

<operation id="17" st_id="1" stage="1" lat="1">
<core>NULL</core>
<MemPortIdVec></MemPortIdVec>
<condition id="0">
<or_exp><and_exp></and_exp></or_exp>
</condition>

<Node id="7" bw="0" op_0_bw="0">
<![CDATA[
:3  br label %.loopexit

]]></Node>
<StgValue><ssdm name=""/></StgValue>
</operation>
</state>

<state id="2" st_id="2">

<operation id="18" st_id="2" stage="1" lat="1">
<core>NULL</core>
<MemPortIdVec></MemPortIdVec>
<condition id="1">
<or_exp><and_exp></and_exp></or_exp>
</condition>

<Node id="9" bw="7" op_0_bw="7" op_1_bw="0">
<![CDATA[
.loopexit:0  %i = phi i7 [ 0, %0 ], [ %i_9, %.loopexit.loopexit ]

]]></Node>
<StgValue><ssdm name="i"/></StgValue>
</operation>

<operation id="19" st_id="2" stage="1" lat="1">
<core>NULL</core>
<MemPortIdVec></MemPortIdVec>
<condition id="1">
<or_exp><and_exp></and_exp></or_exp>
</condition>

<Node id="10" bw="11" op_0_bw="11" op_1_bw="7" op_2_bw="4">
<![CDATA[
.loopexit:1  %tmp = call i11 @_ssdm_op_BitConcatenate.i11.i7.i4(i7 %i, i4 0)

]]></Node>
<StgValue><ssdm name="tmp"/></StgValue>
</operation>

<operation id="20" st_id="2" stage="1" lat="1">
<core>NULL</core>
<MemPortIdVec></MemPortIdVec>
<condition id="1">
<or_exp><and_exp></and_exp></or_exp>
</condition>

<Node id="11" bw="12" op_0_bw="11">
<![CDATA[
.loopexit:2  %tmp_125_cast = zext i11 %tmp to i12

]]></Node>
<StgValue><ssdm name="tmp_125_cast"/></StgValue>
</operation>

<operation id="21" st_id="2" stage="1" lat="1">
<core>Cmp</core>
<MemPortIdVec></MemPortIdVec>
<condition id="1">
<or_exp><and_exp></and_exp></or_exp>
</condition>

<Node id="12" bw="1" op_0_bw="7" op_1_bw="7">
<![CDATA[
.loopexit:3  %exitcond3 = icmp eq i7 %i, -8

]]></Node>
<StgValue><ssdm name="exitcond3"/></StgValue>
</operation>

<operation id="22" st_id="2" stage="1" lat="1">
<core>NULL</core>
<MemPortIdVec></MemPortIdVec>
<condition id="1">
<or_exp><and_exp></and_exp></or_exp>
</condition>

<Node id="13" bw="32" op_0_bw="32" op_1_bw="64" op_2_bw="64" op_3_bw="64">
<![CDATA[
.loopexit:4  %empty = call i32 (...)* @_ssdm_op_SpecLoopTripCount(i64 120, i64 120, i64 120)

]]></Node>
<StgValue><ssdm name="empty"/></StgValue>
</operation>

<operation id="23" st_id="2" stage="1" lat="1">
<core>AddSub</core>
<MemPortIdVec></MemPortIdVec>
<condition id="1">
<or_exp><and_exp></and_exp></or_exp>
</condition>

<Node id="14" bw="7" op_0_bw="7" op_1_bw="7">
<![CDATA[
.loopexit:5  %i_9 = add i7 %i, 1

]]></Node>
<StgValue><ssdm name="i_9"/></StgValue>
</operation>

<operation id="24" st_id="2" stage="1" lat="1">
<core>NULL</core>
<MemPortIdVec></MemPortIdVec>
<condition id="1">
<or_exp><and_exp></and_exp></or_exp>
</condition>

<Node id="15" bw="0" op_0_bw="1" op_1_bw="0" op_2_bw="0">
<![CDATA[
.loopexit:6  br i1 %exitcond3, label %2, label %.preheader5.preheader

]]></Node>
<StgValue><ssdm name=""/></StgValue>
</operation>

<operation id="25" st_id="2" stage="1" lat="1">
<core>NULL</core>
<MemPortIdVec></MemPortIdVec>
<condition id="3">
<or_exp><and_exp><literal name="exitcond3" val="0"/>
</and_exp></or_exp>
</condition>

<Node id="17" bw="0" op_0_bw="0">
<![CDATA[
.preheader5.preheader:0  br label %.preheader5

]]></Node>
<StgValue><ssdm name=""/></StgValue>
</operation>

<operation id="26" st_id="2" stage="1" lat="1">
<core>NULL</core>
<MemPortIdVec></MemPortIdVec>
<condition id="5">
<or_exp><and_exp><literal name="exitcond3" val="1"/>
</and_exp></or_exp>
</condition>

<Node id="67" bw="0">
<![CDATA[
:0  ret void

]]></Node>
<StgValue><ssdm name=""/></StgValue>
</operation>
</state>

<state id="3" st_id="3">

<operation id="27" st_id="3" stage="1" lat="1">
<core>NULL</core>
<MemPortIdVec></MemPortIdVec>
<condition id="6">
<or_exp><and_exp></and_exp></or_exp>
</condition>

<Node id="19" bw="5" op_0_bw="5" op_1_bw="0">
<![CDATA[
.preheader5:0  %j = phi i5 [ %j_7, %.preheader5.loopexit ], [ 0, %.preheader5.preheader ]

]]></Node>
<StgValue><ssdm name="j"/></StgValue>
</operation>

<operation id="28" st_id="3" stage="1" lat="1">
<core>NULL</core>
<MemPortIdVec></MemPortIdVec>
<condition id="6">
<or_exp><and_exp></and_exp></or_exp>
</condition>

<Node id="20" bw="12" op_0_bw="5">
<![CDATA[
.preheader5:1  %j_cast3_cast = zext i5 %j to i12

]]></Node>
<StgValue><ssdm name="j_cast3_cast"/></StgValue>
</operation>

<operation id="29" st_id="3" stage="1" lat="1">
<core>AddSub</core>
<MemPortIdVec></MemPortIdVec>
<condition id="6">
<or_exp><and_exp></and_exp></or_exp>
</condition>

<Node id="21" bw="12" op_0_bw="12" op_1_bw="12">
<![CDATA[
.preheader5:2  %tmp_s = add i12 %tmp_125_cast, %j_cast3_cast

]]></Node>
<StgValue><ssdm name="tmp_s"/></StgValue>
</operation>

<operation id="30" st_id="3" stage="1" lat="1">
<core>NULL</core>
<MemPortIdVec></MemPortIdVec>
<condition id="6">
<or_exp><and_exp></and_exp></or_exp>
</condition>

<Node id="22" bw="32" op_0_bw="12">
<![CDATA[
.preheader5:3  %tmp_126_cast = zext i12 %tmp_s to i32

]]></Node>
<StgValue><ssdm name="tmp_126_cast"/></StgValue>
</operation>

<operation id="31" st_id="3" stage="1" lat="1">
<core>NULL</core>
<MemPortIdVec></MemPortIdVec>
<condition id="6">
<or_exp><and_exp></and_exp></or_exp>
</condition>

<Node id="23" bw="14" op_0_bw="14" op_1_bw="12" op_2_bw="2">
<![CDATA[
.preheader5:4  %tmp_123 = call i14 @_ssdm_op_BitConcatenate.i14.i12.i2(i12 %tmp_s, i2 0)

]]></Node>
<StgValue><ssdm name="tmp_123"/></StgValue>
</operation>

<operation id="32" st_id="3" stage="1" lat="1">
<core>NULL</core>
<MemPortIdVec></MemPortIdVec>
<condition id="6">
<or_exp><and_exp></and_exp></or_exp>
</condition>

<Node id="24" bw="32" op_0_bw="14">
<![CDATA[
.preheader5:5  %p_shl = zext i14 %tmp_123 to i32

]]></Node>
<StgValue><ssdm name="p_shl"/></StgValue>
</operation>

<operation id="33" st_id="3" stage="1" lat="1">
<core>AddSub</core>
<MemPortIdVec></MemPortIdVec>
<condition id="6">
<or_exp><and_exp></and_exp></or_exp>
</condition>

<Node id="25" bw="32" op_0_bw="32" op_1_bw="32">
<![CDATA[
.preheader5:6  %tmp_124 = add i32 %tmp_126_cast, %p_shl

]]></Node>
<StgValue><ssdm name="tmp_124"/></StgValue>
</operation>

<operation id="34" st_id="3" stage="1" lat="1">
<core>Cmp</core>
<MemPortIdVec></MemPortIdVec>
<condition id="6">
<or_exp><and_exp></and_exp></or_exp>
</condition>

<Node id="26" bw="1" op_0_bw="5" op_1_bw="5">
<![CDATA[
.preheader5:7  %exitcond2 = icmp eq i5 %j, -16

]]></Node>
<StgValue><ssdm name="exitcond2"/></StgValue>
</operation>

<operation id="35" st_id="3" stage="1" lat="1">
<core>NULL</core>
<MemPortIdVec></MemPortIdVec>
<condition id="6">
<or_exp><and_exp></and_exp></or_exp>
</condition>

<Node id="27" bw="32" op_0_bw="32" op_1_bw="64" op_2_bw="64" op_3_bw="64">
<![CDATA[
.preheader5:8  %empty_67 = call i32 (...)* @_ssdm_op_SpecLoopTripCount(i64 16, i64 16, i64 16)

]]></Node>
<StgValue><ssdm name="empty_67"/></StgValue>
</operation>

<operation id="36" st_id="3" stage="1" lat="1">
<core>AddSub</core>
<MemPortIdVec></MemPortIdVec>
<condition id="6">
<or_exp><and_exp></and_exp></or_exp>
</condition>

<Node id="28" bw="5" op_0_bw="5" op_1_bw="5">
<![CDATA[
.preheader5:9  %j_7 = add i5 %j, 1

]]></Node>
<StgValue><ssdm name="j_7"/></StgValue>
</operation>

<operation id="37" st_id="3" stage="1" lat="1">
<core>NULL</core>
<MemPortIdVec></MemPortIdVec>
<condition id="6">
<or_exp><and_exp></and_exp></or_exp>
</condition>

<Node id="29" bw="0" op_0_bw="1" op_1_bw="0" op_2_bw="0">
<![CDATA[
.preheader5:10  br i1 %exitcond2, label %.loopexit.loopexit, label %.preheader4.preheader

]]></Node>
<StgValue><ssdm name=""/></StgValue>
</operation>

<operation id="38" st_id="3" stage="1" lat="1">
<core>NULL</core>
<MemPortIdVec></MemPortIdVec>
<condition id="8">
<or_exp><and_exp><literal name="exitcond2" val="0"/>
</and_exp></or_exp>
</condition>

<Node id="31" bw="0" op_0_bw="0">
<![CDATA[
.preheader4.preheader:0  br label %.preheader4

]]></Node>
<StgValue><ssdm name=""/></StgValue>
</operation>

<operation id="39" st_id="3" stage="1" lat="1">
<core>NULL</core>
<MemPortIdVec></MemPortIdVec>
<condition id="10">
<or_exp><and_exp><literal name="exitcond2" val="1"/>
</and_exp></or_exp>
</condition>

<Node id="65" bw="0" op_0_bw="0">
<![CDATA[
.loopexit.loopexit:0  br label %.loopexit

]]></Node>
<StgValue><ssdm name=""/></StgValue>
</operation>
</state>

<state id="4" st_id="4">

<operation id="40" st_id="4" stage="1" lat="1">
<core>NULL</core>
<MemPortIdVec></MemPortIdVec>
<condition id="11">
<or_exp><and_exp></and_exp></or_exp>
</condition>

<Node id="33" bw="3" op_0_bw="3" op_1_bw="0">
<![CDATA[
.preheader4:0  %k = phi i3 [ %k_4, %.preheader4.loopexit ], [ 0, %.preheader4.preheader ]

]]></Node>
<StgValue><ssdm name="k"/></StgValue>
</operation>

<operation id="41" st_id="4" stage="1" lat="1">
<core>NULL</core>
<MemPortIdVec></MemPortIdVec>
<condition id="11">
<or_exp><and_exp></and_exp></or_exp>
</condition>

<Node id="34" bw="32" op_0_bw="3">
<![CDATA[
.preheader4:1  %k_cast2 = zext i3 %k to i32

]]></Node>
<StgValue><ssdm name="k_cast2"/></StgValue>
</operation>

<operation id="42" st_id="4" stage="1" lat="1">
<core>AddSub</core>
<MemPortIdVec></MemPortIdVec>
<condition id="11">
<or_exp><and_exp></and_exp></or_exp>
</condition>

<Node id="35" bw="32" op_0_bw="32" op_1_bw="32">
<![CDATA[
.preheader4:2  %tmp_125 = add i32 %tmp_124, %k_cast2

]]></Node>
<StgValue><ssdm name="tmp_125"/></StgValue>
</operation>

<operation id="43" st_id="4" stage="1" lat="1">
<core>NULL</core>
<MemPortIdVec></MemPortIdVec>
<condition id="11">
<or_exp><and_exp></and_exp></or_exp>
</condition>

<Node id="36" bw="32" op_0_bw="32" op_1_bw="32">
<![CDATA[
.preheader4:3  %tmp_126 = shl i32 %tmp_125, 2

]]></Node>
<StgValue><ssdm name="tmp_126"/></StgValue>
</operation>

<operation id="44" st_id="4" stage="1" lat="1">
<core>AddSub</core>
<MemPortIdVec></MemPortIdVec>
<condition id="11">
<or_exp><and_exp></and_exp></or_exp>
</condition>

<Node id="37" bw="32" op_0_bw="32" op_1_bw="32">
<![CDATA[
.preheader4:4  %tmp_127 = add i32 %tmp_125, %tmp_126

]]></Node>
<StgValue><ssdm name="tmp_127"/></StgValue>
</operation>

<operation id="45" st_id="4" stage="1" lat="1">
<core>Cmp</core>
<MemPortIdVec></MemPortIdVec>
<condition id="11">
<or_exp><and_exp></and_exp></or_exp>
</condition>

<Node id="38" bw="1" op_0_bw="3" op_1_bw="3">
<![CDATA[
.preheader4:5  %exitcond1 = icmp eq i3 %k, -3

]]></Node>
<StgValue><ssdm name="exitcond1"/></StgValue>
</operation>

<operation id="46" st_id="4" stage="1" lat="1">
<core>NULL</core>
<MemPortIdVec></MemPortIdVec>
<condition id="11">
<or_exp><and_exp></and_exp></or_exp>
</condition>

<Node id="39" bw="32" op_0_bw="32" op_1_bw="64" op_2_bw="64" op_3_bw="64">
<![CDATA[
.preheader4:6  %empty_68 = call i32 (...)* @_ssdm_op_SpecLoopTripCount(i64 5, i64 5, i64 5)

]]></Node>
<StgValue><ssdm name="empty_68"/></StgValue>
</operation>

<operation id="47" st_id="4" stage="1" lat="1">
<core>AddSub</core>
<MemPortIdVec></MemPortIdVec>
<condition id="11">
<or_exp><and_exp></and_exp></or_exp>
</condition>

<Node id="40" bw="3" op_0_bw="3" op_1_bw="3">
<![CDATA[
.preheader4:7  %k_4 = add i3 1, %k

]]></Node>
<StgValue><ssdm name="k_4"/></StgValue>
</operation>

<operation id="48" st_id="4" stage="1" lat="1">
<core>NULL</core>
<MemPortIdVec></MemPortIdVec>
<condition id="11">
<or_exp><and_exp></and_exp></or_exp>
</condition>

<Node id="41" bw="0" op_0_bw="1" op_1_bw="0" op_2_bw="0">
<![CDATA[
.preheader4:8  br i1 %exitcond1, label %.preheader5.loopexit, label %.preheader.preheader

]]></Node>
<StgValue><ssdm name=""/></StgValue>
</operation>

<operation id="49" st_id="4" stage="1" lat="1">
<core>AddSub</core>
<MemPortIdVec></MemPortIdVec>
<condition id="13">
<or_exp><and_exp><literal name="exitcond1" val="0"/>
</and_exp></or_exp>
</condition>

<Node id="43" bw="32" op_0_bw="32" op_1_bw="32">
<![CDATA[
.preheader.preheader:0  %tmp_128 = add i32 %tmp_127, %c5_w_i11_cast

]]></Node>
<StgValue><ssdm name="tmp_128"/></StgValue>
</operation>

<operation id="50" st_id="4" stage="1" lat="1">
<core>NULL</core>
<MemPortIdVec></MemPortIdVec>
<condition id="15">
<or_exp><and_exp><literal name="exitcond1" val="1"/>
</and_exp></or_exp>
</condition>

<Node id="63" bw="0" op_0_bw="0">
<![CDATA[
.preheader5.loopexit:0  br label %.preheader5

]]></Node>
<StgValue><ssdm name=""/></StgValue>
</operation>
</state>

<state id="5" st_id="5">

<operation id="51" st_id="5" stage="1" lat="1">
<core>NULL</core>
<MemPortIdVec></MemPortIdVec>
<condition id="16">
<or_exp><and_exp></and_exp></or_exp>
</condition>

<Node id="44" bw="32" op_0_bw="32" op_1_bw="32">
<![CDATA[
.preheader.preheader:1  %in_addr = getelementptr float* %in_r, i32 %tmp_128

]]></Node>
<StgValue><ssdm name="in_addr"/></StgValue>
</operation>

<operation id="52" st_id="5" stage="7" lat="7">
<core>m_axi</core>
<MemPortIdVec></MemPortIdVec>
<condition id="16">
<or_exp><and_exp></and_exp></or_exp>
</condition>

<Node id="45" bw="1" op_0_bw="1" op_1_bw="32" op_2_bw="32">
<![CDATA[
.preheader.preheader:2  %p_rd_req = call i1 @_ssdm_op_ReadReq.m_axi.floatP(float* %in_addr, i32 5)

]]></Node>
<StgValue><ssdm name="p_rd_req"/></StgValue>
</operation>
</state>

<state id="6" st_id="6">

<operation id="53" st_id="6" stage="6" lat="7">
<core>m_axi</core>
<MemPortIdVec></MemPortIdVec>
<condition id="17">
<or_exp><and_exp></and_exp></or_exp>
</condition>

<Node id="45" bw="1" op_0_bw="1" op_1_bw="32" op_2_bw="32">
<![CDATA[
.preheader.preheader:2  %p_rd_req = call i1 @_ssdm_op_ReadReq.m_axi.floatP(float* %in_addr, i32 5)

]]></Node>
<StgValue><ssdm name="p_rd_req"/></StgValue>
</operation>
</state>

<state id="7" st_id="7">

<operation id="54" st_id="7" stage="5" lat="7">
<core>m_axi</core>
<MemPortIdVec></MemPortIdVec>
<condition id="18">
<or_exp><and_exp></and_exp></or_exp>
</condition>

<Node id="45" bw="1" op_0_bw="1" op_1_bw="32" op_2_bw="32">
<![CDATA[
.preheader.preheader:2  %p_rd_req = call i1 @_ssdm_op_ReadReq.m_axi.floatP(float* %in_addr, i32 5)

]]></Node>
<StgValue><ssdm name="p_rd_req"/></StgValue>
</operation>
</state>

<state id="8" st_id="8">

<operation id="55" st_id="8" stage="4" lat="7">
<core>m_axi</core>
<MemPortIdVec></MemPortIdVec>
<condition id="19">
<or_exp><and_exp></and_exp></or_exp>
</condition>

<Node id="45" bw="1" op_0_bw="1" op_1_bw="32" op_2_bw="32">
<![CDATA[
.preheader.preheader:2  %p_rd_req = call i1 @_ssdm_op_ReadReq.m_axi.floatP(float* %in_addr, i32 5)

]]></Node>
<StgValue><ssdm name="p_rd_req"/></StgValue>
</operation>
</state>

<state id="9" st_id="9">

<operation id="56" st_id="9" stage="3" lat="7">
<core>m_axi</core>
<MemPortIdVec></MemPortIdVec>
<condition id="20">
<or_exp><and_exp></and_exp></or_exp>
</condition>

<Node id="45" bw="1" op_0_bw="1" op_1_bw="32" op_2_bw="32">
<![CDATA[
.preheader.preheader:2  %p_rd_req = call i1 @_ssdm_op_ReadReq.m_axi.floatP(float* %in_addr, i32 5)

]]></Node>
<StgValue><ssdm name="p_rd_req"/></StgValue>
</operation>
</state>

<state id="10" st_id="10">

<operation id="57" st_id="10" stage="2" lat="7">
<core>m_axi</core>
<MemPortIdVec></MemPortIdVec>
<condition id="21">
<or_exp><and_exp></and_exp></or_exp>
</condition>

<Node id="45" bw="1" op_0_bw="1" op_1_bw="32" op_2_bw="32">
<![CDATA[
.preheader.preheader:2  %p_rd_req = call i1 @_ssdm_op_ReadReq.m_axi.floatP(float* %in_addr, i32 5)

]]></Node>
<StgValue><ssdm name="p_rd_req"/></StgValue>
</operation>
</state>

<state id="11" st_id="11">

<operation id="58" st_id="11" stage="1" lat="7">
<core>m_axi</core>
<MemPortIdVec></MemPortIdVec>
<condition id="22">
<or_exp><and_exp></and_exp></or_exp>
</condition>

<Node id="45" bw="1" op_0_bw="1" op_1_bw="32" op_2_bw="32">
<![CDATA[
.preheader.preheader:2  %p_rd_req = call i1 @_ssdm_op_ReadReq.m_axi.floatP(float* %in_addr, i32 5)

]]></Node>
<StgValue><ssdm name="p_rd_req"/></StgValue>
</operation>

<operation id="59" st_id="11" stage="1" lat="1">
<core>NULL</core>
<MemPortIdVec></MemPortIdVec>
<condition id="22">
<or_exp><and_exp></and_exp></or_exp>
</condition>

<Node id="46" bw="0" op_0_bw="0">
<![CDATA[
.preheader.preheader:3  br label %.preheader

]]></Node>
<StgValue><ssdm name=""/></StgValue>
</operation>
</state>

<state id="12" st_id="12">

<operation id="60" st_id="12" stage="1" lat="1">
<core>NULL</core>
<MemPortIdVec></MemPortIdVec>
<condition id="23">
<or_exp><and_exp></and_exp></or_exp>
</condition>

<Node id="48" bw="3" op_0_bw="3" op_1_bw="0">
<![CDATA[
.preheader:0  %l = phi i3 [ %l_1, %1 ], [ 0, %.preheader.preheader ]

]]></Node>
<StgValue><ssdm name="l"/></StgValue>
</operation>

<operation id="61" st_id="12" stage="1" lat="1">
<core>NULL</core>
<MemPortIdVec></MemPortIdVec>
<condition id="23">
<or_exp><and_exp></and_exp></or_exp>
</condition>

<Node id="49" bw="32" op_0_bw="3">
<![CDATA[
.preheader:1  %l_cast1 = zext i3 %l to i32

]]></Node>
<StgValue><ssdm name="l_cast1"/></StgValue>
</operation>

<operation id="62" st_id="12" stage="1" lat="1">
<core>AddSub</core>
<MemPortIdVec></MemPortIdVec>
<condition id="23">
<or_exp><and_exp></and_exp></or_exp>
</condition>

<Node id="50" bw="32" op_0_bw="32" op_1_bw="32">
<![CDATA[
.preheader:2  %tmp_129 = add i32 %l_cast1, %tmp_127

]]></Node>
<StgValue><ssdm name="tmp_129"/></StgValue>
</operation>

<operation id="63" st_id="12" stage="1" lat="1">
<core>NULL</core>
<MemPortIdVec></MemPortIdVec>
<condition id="23">
<or_exp><and_exp></and_exp></or_exp>
</condition>

<Node id="51" bw="16" op_0_bw="32" op_1_bw="32" op_2_bw="32">
<![CDATA[
.preheader:3  %out_addr = getelementptr [48000 x float]* %out_r, i32 0, i32 %tmp_129

]]></Node>
<StgValue><ssdm name="out_addr"/></StgValue>
</operation>

<operation id="64" st_id="12" stage="1" lat="1">
<core>Cmp</core>
<MemPortIdVec></MemPortIdVec>
<condition id="23">
<or_exp><and_exp></and_exp></or_exp>
</condition>

<Node id="52" bw="1" op_0_bw="3" op_1_bw="3">
<![CDATA[
.preheader:4  %exitcond = icmp eq i3 %l, -3

]]></Node>
<StgValue><ssdm name="exitcond"/></StgValue>
</operation>

<operation id="65" st_id="12" stage="1" lat="1">
<core>NULL</core>
<MemPortIdVec></MemPortIdVec>
<condition id="23">
<or_exp><and_exp></and_exp></or_exp>
</condition>

<Node id="53" bw="32" op_0_bw="32" op_1_bw="64" op_2_bw="64" op_3_bw="64">
<![CDATA[
.preheader:5  %empty_69 = call i32 (...)* @_ssdm_op_SpecLoopTripCount(i64 5, i64 5, i64 5)

]]></Node>
<StgValue><ssdm name="empty_69"/></StgValue>
</operation>

<operation id="66" st_id="12" stage="1" lat="1">
<core>AddSub</core>
<MemPortIdVec></MemPortIdVec>
<condition id="23">
<or_exp><and_exp></and_exp></or_exp>
</condition>

<Node id="54" bw="3" op_0_bw="3" op_1_bw="3">
<![CDATA[
.preheader:6  %l_1 = add i3 %l, 1

]]></Node>
<StgValue><ssdm name="l_1"/></StgValue>
</operation>

<operation id="67" st_id="12" stage="1" lat="1">
<core>NULL</core>
<MemPortIdVec></MemPortIdVec>
<condition id="23">
<or_exp><and_exp></and_exp></or_exp>
</condition>

<Node id="55" bw="0" op_0_bw="1" op_1_bw="0" op_2_bw="0">
<![CDATA[
.preheader:7  br i1 %exitcond, label %.preheader4.loopexit, label %1

]]></Node>
<StgValue><ssdm name=""/></StgValue>
</operation>

<operation id="68" st_id="12" stage="1" lat="1">
<core>m_axi</core>
<MemPortIdVec></MemPortIdVec>
<condition id="25">
<or_exp><and_exp><literal name="exitcond" val="0"/>
</and_exp></or_exp>
</condition>

<Node id="57" bw="32" op_0_bw="32" op_1_bw="32">
<![CDATA[
:0  %in_addr_read = call float @_ssdm_op_Read.m_axi.floatP(float* %in_addr)

]]></Node>
<StgValue><ssdm name="in_addr_read"/></StgValue>
</operation>

<operation id="69" st_id="12" stage="1" lat="1">
<core>NULL</core>
<MemPortIdVec></MemPortIdVec>
<condition id="27">
<or_exp><and_exp><literal name="exitcond" val="1"/>
</and_exp></or_exp>
</condition>

<Node id="61" bw="0" op_0_bw="0">
<![CDATA[
.preheader4.loopexit:0  br label %.preheader4

]]></Node>
<StgValue><ssdm name=""/></StgValue>
</operation>
</state>

<state id="13" st_id="13">

<operation id="70" st_id="13" stage="1" lat="1">
<core>RAM</core>
<MemPortIdVec></MemPortIdVec>
<condition id="28">
<or_exp><and_exp></and_exp></or_exp>
</condition>

<Node id="58" bw="0" op_0_bw="32" op_1_bw="16">
<![CDATA[
:1  store float %in_addr_read, float* %out_addr, align 4

]]></Node>
<StgValue><ssdm name=""/></StgValue>
</operation>

<operation id="71" st_id="13" stage="1" lat="1">
<core>NULL</core>
<MemPortIdVec></MemPortIdVec>
<condition id="28">
<or_exp><and_exp></and_exp></or_exp>
</condition>

<Node id="59" bw="0" op_0_bw="0">
<![CDATA[
:2  br label %.preheader

]]></Node>
<StgValue><ssdm name=""/></StgValue>
</operation>
</state>
</state_list>


<ports>
</ports>


<dataflows>
</dataflows>


</stg>
